setup.py
aryantdistributions/Binomialdistribution.py
aryantdistributions/Gaussiandistribution.py
aryantdistributions/Generaldistribution.py
aryantdistributions/__init__.py
aryantdistributions.egg-info/PKG-INFO
aryantdistributions.egg-info/SOURCES.txt
aryantdistributions.egg-info/dependency_links.txt
aryantdistributions.egg-info/not-zip-safe
aryantdistributions.egg-info/top_level.txt