Metadata-Version: 1.0
Name: aryantdistributions
Version: 0.1
Summary: Gaussian distributions
Home-page: UNKNOWN
Author: Aryan Tanwar
Author-email: tanwararyan11@gmail.com
License: UNKNOWN
Platform: UNKNOWN
